{
  "schedule": "- 日経225決算予定:\n    - 05/20(水): 東京海上ホールディングス, ＭＳ＆ＡＤインシュアランスＧＨＤ, ＳＯＭＰＯホールディングス\n    - 06/04(木): 積水ハウス\n- 米S&P500決算予定:\n    - 05/20(Wed): エヌビディア, アナログ・デバイセズ, The TJX Companies, Inc., Lowe's Companies, Inc., インテュイット, Target Corporation, Nordson Corporation\n    - 05/21(Thu): ウォルマート・ストアーズ, Deere & Company, ロス・ストアーズ, テイクツー・インタラクティブ, ワークデイ, コパート, Ralph Lauren Corporation, Deckers Outdoor Corporation\n    - 05/26(Tue): AutoZone, Inc., ゼットスケーラー\n    - 05/27(Wed): マーベル・テクノロジー, セールスフォース, ピンドゥオドゥオ, シノプシス, Agilent Technologies, Inc., ヒューレット・パッカード, Bath & Body Works, Inc.\n    - 05/28(Thu): コストコホールセール, オートデスク, NetApp インク, Dollar Tree, Inc., ベスト・バイ, Hormel Foods Corporation\n    - 06/01(Mon): Hewlett Packard Enterprise Company\n- 市場休日:\n    - 05/25(月): アメリカ (メモリアルデー), イギリス (スプリング・バンクホリデー), 韓国 (ウェーサーカ祭), 香港 (ブッダの誕生日)\n    - 05/27(水): シンガポール (イド・アル＝アドハー)\n    - 05/28(木): インド (イード・アル＝アドハー)\n    - 06/04(木): ブラジル (聖体の祝日)\n    - 06/12(金): ロシア (ロシアの日)\n    - 06/19(金): アメリカ (Juneteenth), 中国 (龍舟節), 台湾 (龍舟節), 香港 (ドラゴンボートフェスティバル)\n    - 06/26(金): インド (元日)\n    - 07/01(水): 香港 (香港特別行政区設立の日)\n    - 07/03(金): アメリカ (独立記念日)\n    - 07/20(月): 日本 (海の日)\n    - 08/10(月): シンガポール (建国記念日)\n- その他の主要イベント:\n    - 05/20(水) 11:00 国内: 日立が「フィジカルAIデー」開催\n    - 05/20(水) 14:00 国内: 石油連盟会長が会見\n    - 05/20(水) 27:00 米国: 連邦公開市場委員会(FOMC)議事要旨(4月28-29日会合分)\n    - 05/21(木) 14:00 国内: 4月首都圏新築マンション発売\n    - 05/27(水) 国内: 配当・優待権利付き最終売買日\n- 経済指標発表予定:\n    - 5/18(月) 11:00 中国4月鉱工業生産指数\n    - 5/18(月) 11:00 中国4月小売売上高\n    - 5/18(月) 11:00 中国4月固定資産投資\n    - 5/18(月) 23:00 米5月NAHB住宅市場指数\n    - 5/19(火) 5:00 米3月対米証券投資\n    - 5/19(火) 8:50 1-3月期GDP1次速報\n    - 5/19(火) 13:30 3月第3次産業活動指数\n    - 5/19(火) 23:00 米4月NAR仮契約住宅販売指数\n    - 5/21(木) 8:50 3月機械受注\n    - 5/21(木) 8:50 4月貿易統計\n    - 5/21(木) 21:30 米4月住宅着工件数\n    - 5/21(木) 21:30 米4月建設許可件数\n    - 5/21(木) 21:30 米5月フィラデルフィア連銀製造業景気指数\n    - 5/22(金) 8:30 4月消費者物価指数(CPI)\n    - 5/22(金) 23:00 米5月ミシガン大学消費者態度指数\n    - 5/25(月) 14:30 4月全国百貨店売上高\n    - 5/26(火) 22:00 米3月住宅価格指数\n    - 5/26(火) 22:00 米3月ケース・シラー米住宅価格指数\n    - 5/26(火) 23:00 米5月消費者信頼感指数(コンファレンス・ボード)\n    - 5/27(水) 8:50 4月企業向けサービス価格指数\n    - 5/27(水) 23:00 米5月リッチモンド連銀製造業指数\n    - 5/28(木) 21:30 米4月耐久財受注\n    - 5/28(木) 21:30 米1-3月期GDP改定値\n    - 5/28(木) 22:30 米4月個人所得\n    - 5/28(木) 22:30 米4月個人消費支出(PCE)\n    - 5/28(木) 22:30 米4月個人消費支出(PCEデフレーター)\n    - 5/28(木) 23:00 米4月新築住宅販売件数\n    - 5/29(金) 8:30 5月東京都区部消費者物価指数(CPI)\n    - 5/29(金) 8:30 4月失業率\n    - 5/29(金) 8:30 4月有効求人倍率\n    - 5/29(金) 8:50 4月鉱工業生産指数\n    - 5/29(金) 8:50 4月商業動態統計\n    - 5/31(日) 中国5月製造業購買担当者景気指数(PMI)\n    - 06/01(月) 22:45 05月 製造業PMI（購買担当者景気指数・確報値）\n    - 06/01(月) 23:00 05月 ISM製造業景気指数\n    - 06/02(火) 23:00 04月 JOLTS求人件数",
  "indices": {
    "日本日経平均": {
      "price": "59,804.41",
      "change": "-1.23%"
    },
    "日経先物": {
      "price": "60,165.00",
      "change": "-0.83%"
    },
    "為替 ドル円": {
      "price": "159.07",
      "change": "0.13%"
    },
    "為替 ユーロ円": {
      "price": "184.38",
      "change": "-0.42%"
    },
    "米国NYダウ": {
      "price": "49,363.88",
      "change": "-0.65%"
    },
    "VIX恐怖指数": {
      "price": "18.00",
      "change": "-0.33%"
    },
    "WTI原油先物": {
      "price": "102.43",
      "change": "-4.95%"
    },
    "NY金先物": {
      "price": "4,481.90",
      "change": "-0.54%"
    },
    "ビットコイン": {
      "price": "12,302,711.00",
      "change": "0.78%"
    },
    "日本TOPIX": {
      "price": "402.20 (ETF)",
      "change": "-1.49%"
    },
    "日本国債10年利回り": {
      "price": "2.783%",
      "change": "0.054pt"
    }
  },
  "news": "- 05/19(火) 07:45 第1四半期 生産者物価指数（PPI）[前期比]: 0.8%\n- 05/19(火) 08:50 第1四半期 実質GDP[前期比年率]: 2.1%\n- 05/19(火) 08:50 第1四半期 実質GDP[前期比]: 0.5%\n- 05/19(火) 08:50 第1四半期 GDPデフレータ[前年比]: 3.4%\n- 05/19(火) 09:30 05月 Westpac消費者信頼感指数[前月比]: 3.5%\n- 05/19(火) 13:30 03月 設備稼働率[前月比]: -1.2%\n- 05/19(火) 13:30 03月 鉱工業生産[前月比]: -0.4%\n- 05/19(火) 13:30 03月 鉱工業生産[前年比]: 2.4%\n- 05/19(火) 13:30 03月 第3次産業活動指数[前月比]: -0.2%\n- 05/19(火) 15:00 03月 ILO雇用統計（失業率）: 5.0%\n- 05/19(火) 15:00 04月 雇用統計（失業率）: 4.4%\n- 05/19(火) 15:00 04月 失業保険申請件数[前月比]: 2.65万件\n- 05/19(火) 17:30 04月 雇用統計（失業率）: 3.7%\n- 05/19(火) 18:00 03月 ユーロ圏貿易収支（季調済）: 35.0億ユーロ\n- 05/19(火) 18:00 03月 ユーロ圏貿易収支（季調前）: 78.0億ユーロ\n- 05/19(火) 21:30 04月 消費者物価指数（CPI）[前月比]: 0.4%\n- 05/19(火) 21:30 04月 消費者物価指数（CPI）[前年比]: 2.8%\n- 05/19(火) 21:30 03月 住宅建設許可[前月比]: 10.3%\n- 05/19(火) 23:00 04月 中古住宅販売成約指数[前月比]: 1.4%\n- 05/19(火) 23:00 04月 中古住宅販売成約指数[前年比]: 3.3%\n- 05/20(水) 10:00 05月 中国最優遇貸出金利(ローンプライムﾚｰﾄ 5年): 3.5%\n- 05/20(水) 10:00 05月 中国最優遇貸出金利(ローンプライムﾚｰﾄ 1年): 3.0%\n- 05/20(水) 15:00 04月 消費者物価指数（CPI）[前月比]: 0.7%\n- 05/20(水) 15:00 04月 消費者物価指数（CPI）[前年比]: 2.8%\n- 05/20(水) 15:00 04月 消費者物価指数（CPI）（コア）[前年比]: 2.5%\n- 05/20(水) 15:00 04月 小売物価指数（RPI）[前月比]: 0.7%\n- 05/20(水) 15:00 04月 小売物価指数（RPI）[前年比]: 3.0%\n- 05/20(水) 15:00 04月 小売物価指数(RPIX)(除くﾓｰｹﾞｰｼﾞ利払)[前年比]: 3.0%\n- 05/20(水) 15:00 04月 生産者物価指数（PPI）[前月比]: 1.2%\n- 05/20(水) 15:00 04月 生産者物価指数（PPI）[前年比]: 1.7%\n- 05/20(水) 15:00 04月 生産者物価指数（PPI）（出荷）[前月比]: 1.4%\n- 05/20(水) 15:00 04月 生産者物価指数（PPI）（出荷）[前年比]: 4.0%\n- 05/20(水) 15:00 04月 生産者物価指数（PPI）（仕入）[前月比]: 2.4%\n- 05/20(水) 15:00 04月 生産者物価指数（PPI）（仕入）[前年比]: 7.7%\n- 05/20(水) 17:00 04月 消費者物価指数（CPI）（総品目）[前月比]: 1.1%\n- 05/20(水) 17:00 04月 消費者物価指数（CPI）（総品目）[前年比]: 4.0%\n- 05/20(水) 18:00 04月 ユーロ圏消費者物価指数（HICP）[前年比]: 3.0%\n- 05/20(水) 18:00 04月 ユーロ圏消費者物価指数(HICP)(コア)[前年比]: 2.2%\n- 05/20(水) 20:00 03月 小売売上高[前年比]: 2.4%\n- 05/20(水) 20:00 05/09 - 05/15 MBA住宅ローン申請指数[前週比]: 1.7%\n- 05/20(水) 23:30 05/09 - 05/15 原油在庫[前週比]: -430.6万バレル\n- 05/20(水) 23:30 05/09 - 05/15 ガソリン在庫[前週比]: -408.4万バレル\n- 05/20(水) 23:30 05/09 - 05/15 留出油在庫[前週比]: 19.0万バレル\n- 05/20(水) 16:15 国内 訪日外客数(4月): 361.89万人\n- 05/20(水) 20:30 インド インフラ産業8業種(4月): -0.4％",
  "contribution": "- 値上がり寄与TOP50 (2026年05月20日 17:40):\n    - ファーストリテイリング: +87.69\n    - アドバンテスト: +80.86\n    - キオクシアホールディングス: +35.67\n    - イビデン: +21.45\n    - テルモ: +13.01\n    - 大塚ホールディングス: +9.39\n    - 良品計画: +7.91\n    - ＫＤＤＩ: +6.44\n    - ニトリホールディングス: +5.24\n    - オリックス: +4.63\n    - 太陽誘電: +3.12\n    - 京セラ: +2.55\n    - アサヒグループホールディングス: +2.16\n    - 古河電気工業: +2.04\n    - ローム: +1.84\n    - イオン: +1.81\n    - ＵＢＥ: +1.68\n    - ネクソン: +1.27\n    - 日本取引所グループ: +0.97\n    - 千葉銀行: +0.8\n    - しずおかフィナンシャルグループ: +0.74\n    - 塩野義製薬: +0.7\n    - ＳＣＲＥＥＮホールディングス: +0.67\n    - 日本製鋼所: +0.64\n    - 日本郵政: +0.57\n- 値下がり寄与TOP50 (2026年05月20日 17:40):\n    - ソフトバンクグループ: -259.06\n    - 東京エレクトロン: -106.6\n    - フジクラ: -80.45\n    - ファナック: -56.99\n    - 信越化学工業: -31.34\n    - 豊田通商: -29.47\n    - ＴＤＫ: -21.37\n    - リクルートホールディングス: -19.41\n    - ソニーグループ: -19.11\n    - 住友不動産: -13.88\n    - 住友電気工業: -10.56\n    - ベイカレント: -9.52\n    - 三菱電機: -9.15\n    - 安川電機: -8.78\n    - 三菱商事: -8.35\n    - コナミグループ: -7.88\n    - ＳＭＣ: -7.71\n    - スズキ: -7.64\n    - 伊藤忠商事: -7.63\n    - エーザイ: -7.41\n    - 味の素: -7.37\n    - 荏原製作所: -7.31\n    - キーエンス: -7.01\n    - 住友商事: -6.91\n    - 東京海上ホールディングス: -6.64"
}