{
  "schedule": "- **市場休日**\n  - 06/03(水) 韓国 選挙の日\n  - 06/04(木) ブラジル 聖体の祝日\n  - 06/12(金) ロシア ロシアの日\n  - 06/19(金) アメリカ Juneteenth\n  - 06/19(金) 中国 龍舟節\n  - 06/19(金) 台湾 龍舟節\n  - 06/19(金) 香港 ドラゴンボートフェスティバル\n  - 06/26(金) インド 元日\n  - 07/01(水) 香港 香港特別行政区設立の日\n  - 07/03(金) アメリカ 独立記念日\n  - 07/20(月) 日本 海の日\n  - 08/10(月) シンガポール 建国記念日\n  - 08/11(火) 日本 山の日\n  - 08/17(月) 韓国 開放記念日\n  - 08/31(月) イギリス 夏の銀行休日\n- **本日の主な予定 (6月3日)**\n  - **国内**\n    - 09:30 サービス業PMI(5月) 50.0\n    - 09:30 総合PMI(5月) 51.1\n    - 14:00 経団連定時総会\n    - 17:30 植田日本銀行総裁が共同通信社きさらぎ会で講演\n  - **海外**\n    - 10:30 豪・GDP(1-3月) 2.6％\n    - 10:45 [中国] RatingDogサービス業PMI(5月) 52.0\n    - 10:45 [中国] RatingDog総合PMI(5月) 53.1\n    - 14:00 印・サービス業PMI確定値(5月) 58.9\n    - 14:00 印・総合PMI確定値(5月) 58.1\n    - 17:00 ユーロ圏サービス業PMI確報値(5月) 46.4\n    - 17:00 ユーロ圏総合PMI確報値(5月) 47.5\n    - 18:00 ユーロ圏生産者物価指数(4月) 2.1％\n    - 21:00 ブラジル・鉱工業生産(4月) 0.1％\n    - 21:15 [米国] ADP全米雇用報告(5月) 12.0万人\n    - 22:00 ブラジル・サービス業PMI(5月) 52.3\n    - 22:00 ブラジル・総合PMI(5月) 52.4\n    - 22:45 [米国] サービス業PMI確報値(5月) 50.9\n    - 22:45 [米国] 総合PMI確報値(5月) 51.7\n    - 23:00 [米国] ISM非製造業景況指数(5月) 53.6\n    - 23:00 [米国] 製造業受注(4月) 4.3％\n    - 23:00 [米国] 耐久財受注(4月) 7.9％\n    - 27:00 ブラジル・貿易収支(5月) 105.37億ドル\n    - [米国] 地区連銀経済報告(ベージュブック)公表\n    - 第29回サンクトペテルブルク国際経済フォーラム(6日まで)\n- **今週の主な予定**\n  - 6/1(月) 中国5月RatingDog製造業PMI、日本法人企業統計調査、新車/軽自動車販売台数、米5月ISM製造業景況指数\n  - 6/2(火) 5月マネタリーベース、米4月雇用動態調査(JOLTS)求人件数\n  - 6/3(水) 植田日銀総裁講演、米5月ADP雇用統計、米4月製造業新規受注、米5月ISM非製造業景況指数、米地区連銀経済報告(ベージュブック)\n  - 6/4(木) ブロードコム決算\n  - 6/5(金) 4月毎月勤労統計調査、4月家計調査、4月景気動向指数、米5月雇用統計、米4月消費者信用残高\n  - 6/8(月) 1-3月期GDP改定値、5月景気ウォッチャー調査\n  - 6/9(火) 5月マネーストックM2、5月工作機械受注、中国5月貿易収支、米4月貿易収支、米5月中古住宅販売件数\n  - 6/10(水) 5月企業物価指数、中国5月消費者物価指数(CPI)、中国5月生産者物価指数(PPI)、ECB定例理事会、米5月消費者物価指数(CPI)、米5月財政収支\n  - 6/11(木) 4-6月期法人企業景気予測調査、5月都心オフィス空室率、ラガルドECB総裁会見、米5月生産者物価指数(PPI)、FIFAワールドカップ開幕\n  - 6/12(金) メジャーSQ、米6月ミシガン大学消費者態度指数\n- **決算予定**\n  - **日経225採用銘柄**\n    - 06/04(木) 積水ハウス (0.16%)\n  - **米S&P500銘柄**\n    - 06/03(Wed) ブロードコム [AMC]、クラウドストライク・ホールディングス [AMC]、メドトロニック [BMO]\n    - 06/04(Thu) lululemon athletica inc. [AMC]、The Cooper Companies, Inc. [AMC]\n    - 06/08(Mon) The Campbell's Company [BMO]\n    - 06/09(Tue) JM スマッカー [BMO]\n    - 06/10(Wed) オラクル [AMC]\n    - 06/11(Thu) アドビシステムズ [AMC]、Lennar Corporation [AMC]",
  "indices": {
    "日本日経平均": {
      "price": "66,734.24",
      "change": "-0.30%"
    },
    "日経先物": {
      "price": "68,110.00",
      "change": "0.84%"
    },
    "為替 ドル円": {
      "price": "160.02",
      "change": "0.24%"
    },
    "為替 ユーロ円": {
      "price": "185.55",
      "change": "-0.11%"
    },
    "米国NYダウ": {
      "price": "50,867.37",
      "change": "-0.86%"
    },
    "VIX恐怖指数": {
      "price": "16.43",
      "change": "4.19%"
    },
    "WTI原油先物": {
      "price": "96.06",
      "change": "2.45%"
    },
    "NY金先物": {
      "price": "4,466.90",
      "change": "-0.49%"
    },
    "ビットコイン": {
      "price": "10,538,115.00",
      "change": "-1.25%"
    },
    "日本TOPIX": {
      "price": "423.80 (ETF)",
      "change": "1.92%"
    },
    "日本国債10年利回り": {
      "price": "2.577%",
      "change": "-0.105pt"
    }
  },
  "news": "- **06/02(火) 経済指標**\n  - 08:50 05月 マネタリーベース[前年比] 結果 -12.2% (予想 -11.3%)\n  - 10:30 第1四半期 経常収支 -271.0億豪ドル (予想 -211.0億豪ドル)\n  - 10:30 04月 住宅建設許可[前月比] -3.4% (予想 -10.5%)\n  - 15:45 04月 財政収支 -696.0億ユーロ (予想 -429.0億ユーロ)\n  - 17:30 04月 消費者信用残高 19.0億ポンド (予想 19.0億ポンド)\n  - 17:30 04月 マネーサプライM4[前月比] 0.2% (予想 0.8%)\n  - 17:30 04月 マネーサプライM4[前年比] 4.5% (予想 4.3%)\n  - 17:30 04月 小売売上高指数－価額ベース[前年比] 8.6% (予想 12.8%)\n  - 17:30 04月 小売売上高指数－数量ベース[前年比] 6.4% (予想 9.8%)\n  - 17:30 第2四半期 BER企業信頼感 39.0 (予想 47.0)\n  - 18:00 05月 ユーロ圏消費者物価指数（HICP）[前年比] 3.2% (予想 3.3%)\n  - 18:00 05月 ユーロ圏消費者物価指数（HICP）[前月比] 0.1% (予想 0.1%)\n  - 18:00 05月 ユーロ圏消費者物価指数(HICP)(コア)[前年比] 2.5% (予想 2.2%)\n  - 23:00 04月 JOLTS求人件数 761.8万人 (予想 684.8万人)\n- **06/03(水) 経済指標**\n  - 07:45 04月 住宅建設許可[前月比] 10.9% (予想 -1.3%)\n  - 10:30 第1四半期 実質GDP[前期比] 0.3% (予想 0.8%)\n  - 10:30 第1四半期 実質GDP[前年比] 2.5% (予想 2.6%)\n  - 10:45 05月 RatingDogｺﾝﾎﾟｼﾞｯﾄPMI 54.0 (予想 53.1)\n  - 10:45 05月 RatingDogサービス業PMI 54.4 (予想 52.6)\n  - 16:50 05月 サービス業PMI 44.3 (予想 42.9)\n  - 16:55 05月 サービス業PMI 48.1 (予想 47.8)\n  - 17:00 05月 ユーロ圏サービス業PMI 47.7 (予想 46.4)\n  - 17:30 05月 サービス業PMI 49.3 (予想 47.9)\n  - 18:00 04月 ユーロ圏生産者物価指数（PPI）[前月比] 0.6% (予想 0.5%)\n  - 18:00 04月 ユーロ圏生産者物価指数（PPI）[前年比] 4.9% (予想 4.9%)\n  - 20:00 MBA住宅ローン申請指数[前週比] -2.5% (予想 -8.5%)\n  - 21:15 05月 ADP雇用統計[前月比] 12.2万人 (予想 12.0万人)\n  - 21:30 第1四半期 労働生産性[前期比] -0.5% (予想 0.2%)\n  - 22:45 05月 サービス業PMI 50.7 (予想 50.9)\n  - 22:45 05月 ｺﾝﾎﾟｼﾞｯﾄPMI 51.5 (予想 51.7)\n  - 23:00 05月 ISM非製造業景気指数 54.5 (予想 53.8%)\n  - 23:00 04月 製造業新規受注[前月比] 4.8% (予想 4.5%)\n  - 23:00 04月 耐久財受注[前月比] 8.0% (予想 7.9%)\n  - 23:00 04月 耐久財受注（輸送除くコア）[前月比] 1.1% (予想 1.1%)\n  - 23:30 原油在庫[前週比] -797.4万バレル (予想 -300.0万バレル)\n  - 23:30 ガソリン在庫[前週比] 336.4万バレル (予想 -250.0万バレル)\n  - 23:30 留出油在庫[前週比] 150.2万バレル (予想 -200.0万バレル)\n- **06/04(木) 経済指標 (予想・前回のみ)**\n  - 08:50 対外証券投資-中長期ネット 103.0億円\n  - 08:50 対外証券投資-株式ネット -3587.0億円\n  - 08:50 対内証券投資-中長期ネット 13460.0億円\n  - 08:50 対内証券投資-株式ネット 10804.0億円\n  - 10:30 04月 貿易収支 -18.41億豪ドル\n  - 15:30 05月 消費者物価指数（CPI）[前年比] 0.6%\n  - 15:30 05月 消費者物価指数（CPI）[前月比] 0.3%\n  - 16:00 05月 雇用統計（失業率）（季調前） 3.0%\n  - 16:00 05月 雇用統計（失業率）（季調済） 3.0%\n  - 17:30 05月 建設業PMI 39.7\n  - 18:00 04月 ユーロ圏小売売上高[前月比] -0.1%\n  - 18:00 04月 ユーロ圏小売売上高[前年比] 1.2%\n  - 20:30 05月 チャレンジャー人員削減数[前年比] -20.9%\n  - 21:30 第1四半期 非農業部門労働生産性指数[前期比] 0.8%\n  - 21:30 第1四半期 単位労働費用 2.3%\n  - 21:30 新規失業保険申請件数\n  - 21:30 失業保険継続受給者数",
  "contribution": "- **値上がり寄与TOP25 (2026年06月03日 17:40)**\n  - 東京エレクトロン (+723.07)\n  - アドバンテスト (+323.42)\n  - フジクラ (+85.88)\n  - 京セラ (+72.14)\n  - ファナック (+64.03)\n  - 信越化学工業 (+55.81)\n  - ＳＣＲＥＥＮホールディングス (+54.44)\n  - イビデン (+53.97)\n  - ＴＤＫ (+50.79)\n  - ダイキン工業 (+38.05)\n  - レーザーテック (+33.79)\n  - 住友電気工業 (+31.85)\n  - ディスコ (+30.24)\n  - 本田技研工業 (+22.02)\n  - ＨＯＹＡ (+19.95)\n  - 小松製作所 (+19.04)\n  - ＫＤＤＩ (+18.1)\n  - 安川電機 (+17.77)\n  - 太陽誘電 (+17.6)\n  - ローム (+15.62)\n  - 村田製作所 (+15.29)\n  - 富士フイルムホールディングス (+13.38)\n  - キオクシアホールディングス (+12.67)\n  - ルネサスエレクトロニクス (+12.37)\n  - 日本取引所グループ (+12.07)\n- **値下がり寄与TOP25 (2026年06月03日 17:40)**\n  - ソフトバンクグループ (-255.04)\n  - ファーストリテイリング (-101.37)\n  - 中外製薬 (-19.61)\n  - コナミグループ (-10.56)\n  - ソニーグループ (-8.38)\n  - 大塚ホールディングス (-7.37)\n  - 第一三共 (-6.59)\n  - 三井金属 (-6.54)\n  - バンダイナムコホールディングス (-5.13)\n  - 野村総合研究所 (-5.13)\n  - 富士通 (-4.19)\n  - スズキ (-3.75)\n  - メルカリ (-3.45)\n  - 武田薬品工業 (-3.42)\n  - ＳＨＩＦＴ (-3.24)\n  - 三井不動産 (-3.22)\n  - 三越伊勢丹ホールディングス (-2.78)\n  - 日本電気 (-2.7)\n  - 大成建設 (-2.61)\n  - 住友不動産 (-2.41)\n  - ＩＨＩ (-2.39)\n  - 味の素 (-2.35)\n  - エーザイ (-1.98)\n  - 協和キリン (-1.86)\n  - ベイカレント (-1.84)"
}