{
  "schedule": "- 04/06(月) 市場休日:\n  - イギリス、オーストリア、ドイツ、中国、台湾、香港の株式市場は祝日のため休場（復活祭、清明節フェスティバル、墓掃除日）\n- 04/06(月) 本日の主な予定:\n  - 【国内】15:00 石破前首相が講演\n  - 【国内】日本銀行支店長会議 地域経済報告(さくらリポート)(4月、日本銀行)\n  - 【国内】システムエグゼが東証スタンダードに新規上場(公開価格:950円)\n  - 【海外】独・英・豪・仏・NZ・スイス・南ア・株式市場は祝日のため休場(イースターマンデー)\n- 04/07(火) 市場休日:\n  - 香港 復活祭\n- 04/07(火) 今週の主な予定:\n  - 米2月消費者信用残高(4:00)\n  - 2月家計調査(8:30)\n  - 2月景気動向指数(14:00)\n  - 米2月耐久財受注(21:30)\n- 04/08(水) 米S&P500決算予定:\n  - Delta Air Lines, Inc. [BMO]\n  - Constellation Brands, Inc. [AMC]\n- 04/08(水) 今週の主な予定:\n  - FOMC議事録(3/17～18開催分)(3:00)\n  - 2月毎月勤労統計調査(8:30)\n  - 2月国際収支・貿易収支(8:50)\n  - 3月景気ウォッチャー調査(14:00)\n- 04/09(木) 日本決算予定:\n  - ファーストリテイリング (9.74%)\n  - ７＆ｉＨＤ (0.41%)\n  - イオン (0.37%)\n- 04/09(木) 今週の主な予定:\n  - 米イラン戦争交渉期限(9:00)\n  - 3月都心オフィス空室率(13:00)\n  - 3月消費動向調査(14:00)\n  - 3月工作機械受注(15:00)\n  - 米2月個人所得(21:30)\n  - 米2月個人消費支出(PCE)(21:30)\n  - 米2月個人消費支出(PCEデフレーター)(21:30)\n  - 米10-12月期GDP確定値(21:30)\n- 04/10(金) 日本決算予定:\n  - 良品計画 (0.44%)\n  - 安川電機 (0.27%)\n- 04/10(金) 今週の主な予定:\n  - 3月国内企業物価指数(8:50)\n  - オプションSQ\n  - 中国3月消費者物価指数(CPI)(10:30)\n  - 中国3月生産者物価指数(PPI)(10:30)\n  - 米3月消費者物価指数(CPI)(21:30)\n  - 米4月ミシガン大学消費者態度指数(23:00)\n- 04/13(月) 米S&P500決算予定:\n  - ◎*ゴールドマン サックス [BMO]\n  - ファスナル [BMO]\n  - 米国3月中古住宅販売件数(23:00)\n- 04/14(火) 日本決算予定:\n  - ベイカレント (0.30%)\n  - 高島屋 (0.12%)\n  - Ｊ．フロント リテイリング (0.08%)\n  - 東宝 (0.05%)\n  - ＳＨＩＦＴ (0.04%)\n- 04/14(火) 米S&P500決算予定:\n  - ◎*JPモルガン・チェース [BMO]\n  - ◎ジョンソン エンド ジョンソン [BMO]\n  - *シティグループ [BMO]\n  - *ウェルス ファーゴ [BMO]\n  - BlackRock, Inc. [BMO]\n  - CarMax, Inc. [BMO]\n- 04/14(火) 市場休日:\n  - インド Ambedkar Jayanti\n- 04/15(Wed) 米S&P500決算予定:\n  - ASMLホールディング [BMO]\n  - *バンク オブ アメリカ [BMO]\n  - *モルガンスタンレー [BMO]\n  - The Progressive Corporation [BMO]\n  - The PNC Financial Services Group, Inc. [BMO]\n  - Kinder Morgan, Inc. [AMC]\n  - M&T Bank Corporation [BMO]\n  - J.B. Hunt Transport Services, Inc. [AMC]\n- 04/16(Thu) 米S&P500決算予定:\n  - ※ネットフリックス [AMC]\n  - ペプシコ [BMO]\n  - Abbott Laboratories [BMO]\n  - *チャールズ・シュワブ [BMO]\n  - Prologis, Inc. [BMO]\n  - *バンク オブ ニューヨーク [BMO]\n  - *USバンコープ [BMO]\n  - ◎トラベラーズ・カンパニーズ [BMO]\n  - Citizens Financial Group, Inc. [BMO]\n  - KeyCorp [BMO]\n  - Snap-on Incorporated [BMO]\n  - Marsh & McLennan Companies, Inc. [BMO]\n- 04/16(木) 今週の主な予定:\n  - 第1四半期 実質ＧＤＰ [前年比]\n  - 04月 フィラデルフィア連銀景況指数\n  - 03月 鉱工業生産指数 [前月比]\n  - 03月 鉱工業生産指数 [設備稼働率]\n- 04/21(火) 市場休日:\n  - ブラジル ティラデンテスデー\n- 04/22(水) 日本決算予定:\n  - ディスコ (0.83%)\n- 04/23(木) 日本決算予定:\n  - キヤノン (0.42%)\n- 04/24(金) 日本決算予定:\n  - ファナック (1.74%)\n  - 中外製薬 (1.66%)\n  - アステラス製薬 (0.82%)\n  - キッコーマン (0.49%)\n  - キーエンス (0.36%)\n  - 日立建機 (0.34%)\n  - 野村総合研究所 (0.28%)\n  - 富士通 (0.21%)\n  - 富士電機 (0.14%)\n  - ルネサスエレクトロニクス (0.14%)\n- 04/29(水) 市場休日:\n  - 日本 昭和の日\n- 05/01(金) 市場休日:\n  - インド Maharashtra Day\n  - オーストリア 勤労感謝の日\n  - シンガポール 勤労感謝の日\n  - ドイツ 勤労感謝の日\n  - ブラジル 労働者の日\n  - ロシア 勤労感謝の日\n  - 中国 勤労感謝の日\n  - 台湾 勤労感謝の日\n  - 香港 勤労感謝の日\n- 05/04(月) 市場休日:\n  - イギリス 5月上旬銀行休日\n  - 中国 勤労感謝の日\n  - 日本 みどりの日\n- 05/05(火) 市場休日:\n  - 中国 勤労感謝の日\n  - 日本 こどもの日\n  - 韓国 こどもの日\n- 05/06(水) 市場休日:\n  - 日本 憲法記念日\n- 05/09(土) 市場休日:\n  - ロシア 戦勝記念日",
  "indices": {
    "日本日経平均": {
      "price": "53,515.99",
      "change": "0.74%"
    },
    "日経先物": {
      "price": "53,690.00",
      "change": "0.74%"
    },
    "為替 ドル円": {
      "price": "159.54",
      "change": "0.03%"
    },
    "為替 ユーロ円": {
      "price": "183.90",
      "change": "-0.08%"
    },
    "米国NYダウ": {
      "price": "46,504.67",
      "change": "-0.13%"
    },
    "VIX恐怖指数": {
      "price": "23.87",
      "change": "-2.73%"
    },
    "WTI原油先物": {
      "price": "111.35",
      "change": "-0.17%"
    },
    "NY金先物": {
      "price": "4,684.70",
      "change": "0.71%"
    },
    "ビットコイン": {
      "price": "11,048,441.00",
      "change": "2.84%"
    },
    "日本TOPIX": {
      "price": "386.90 (ETF)",
      "change": "0.08%"
    },
    "日本国債10年利回り": {
      "price": "2.386%",
      "change": "-0.009pt"
    }
  },
  "news": "- 04/03(金) 10:45 RatingDog 03月 ｺﾝﾎﾟｼﾞｯﾄPMI（購買担当者指数） 結果: 51.5 (予想: 55.4)\n- 04/03(金) 10:45 RatingDog 03月 サービス業PMI（購買担当者指数） 結果: 52.1 (予想: 53.7)\n- 04/03(金) 15:45 日本 02月 鉱工業生産指数[前月比] 結果: -0.7% (予想: 0.7%)\n- 04/03(金) 21:30 米国 03月 雇用統計（非農業部門雇用者数）[前月比] 結果: 17.8万人 (予想: 6.0万人)\n- 04/03(金) 21:30 米国 03月 雇用統計（平均時給）[前月比] 結果: 0.2% (予想: 0.4%)\n- 04/03(金) 21:30 米国 03月 雇用統計（平均時給）[前年比] 結果: 3.5% (予想: 3.8%)\n- 04/03(金) 21:30 米国 03月 雇用統計（失業率） 結果: 4.3% (予想: 4.4%)\n- 04/03(金) 22:45 米国 03月 サービス業PMI（購買担当者景気指数） 結果: 49.8 (予想: 51.1)\n- 04/03(金) 22:45 米国 03月 ｺﾝﾎﾟｼﾞｯﾄPMI（購買担当者景気指数） 結果: 50.3 (予想: 51.4)\n- 04/06(月) 14:00 日本 02月 小売売上高[前年比] 結果: 8.3% (予想: 3.2%)\n- 04/06(月) 14:00 日本 02月 小売売上高[前月比] 結果: -4.1% (予想: -)\n- 04/06(月) 23:00 米国 03月 ISM非製造業景気指数 結果: 55.0 (予想: 56.1)\n- 04/07(火) 08:30 日本 02月 全世帯家計調査[前年比] 結果: -0.7% (予想: -1.0%)\n- 04/07(火) 14:00 日本 02月 景気先行指数 結果: 111.9 (予想: 112.1)\n- 04/07(火) 14:00 日本 02月 景気一致指数 結果: 116.5 (予想: 117.9)\n- 04/07(火) 16:50 ユーロ圏 03月 サービス業PMI 結果: 48.3 (予想: 48.3)\n- 04/07(火) 16:55 ドイツ 03月 サービス業PMI（購買担当者景気指数） 結果: 51.2 (予想: 51.2)\n- 04/07(火) 17:00 ユーロ圏 03月 ユーロ圏サービス業PMI（購買担当者景気指数） 結果: 50.1 (予想: 50.1)\n- 04/07(火) 17:30 イギリス 03月 サービス業PMI（購買担当者景気指数） 結果: 51.2 (予想: 51.2)\n- 04/07(火) 21:30 米国 02月 耐久財受注[前月比] 結果: -1.0% (予想: 0.0%)\n- 04/07(火) 21:30 米国 02月 耐久財受注（輸送除くコア）[前月比] 結果: 0.6% (予想: 0.4%)\n- 04/07(火) 23:00 カナダ 03月 Ivey購買部協会指数 結果: 56.6 (予想: -)\n- 04/08(水) 11:00 ニュージーランド 04月 NZ中銀政策金利 結果: 2.25% (予想: 2.25%)\n- 04/09(木) 21:30 米国 02月 PCE価格指数[前年比] 結果: 2.8% (予想: 2.8%)\n- 04/09(木) 21:30 米国 02月 コアPCE価格指数[前年比] 結果: 2.9% (予想: 3.1%)\n- 04/09(木) 21:30 米国 第4四半期 実質GDP[前期比年率] 結果: 0.7% (予想: 0.7%)",
  "contribution": "- 日経225 値上がり寄与TOP25 (2026年04月06日 15:00):\n  - アドバンテスト: +123.09\n  - ファーストリテイリング: +55.51\n  - 東京エレクトロン: +43.24\n  - ソフトバンクグループ: +41.84\n  - イビデン: +25.88\n  - 信越化学工業: +21.62\n  - レーザーテック: +20.65\n  - キオクシアホールディングス: +20.41\n  - ＴＤＫ: +13.33\n  - ディスコ: +12.67\n  - 中外製薬: +9.86\n  - ＨＯＹＡ: +8.55\n  - 良品計画: +7.71\n  - 住友電気工業: +7.04\n  - 京セラ: +6.84\n  - 太陽誘電: +5.93\n  - 古河電気工業: +5.7\n  - ＫＤＤＩ: +5.03\n  - 村田製作所: +4.99\n  - ＳＣＲＥＥＮホールディングス: +4.85\n  - 味の素: +4.02\n  - 任天堂: +3.89\n  - ＳＭＣ: +3.86\n  - エーザイ: +3.59\n  - フジクラ: +3.42\n- 日経225 値下がり寄与TOP25 (2026年04月06日 15:00):\n  - ソニーグループ: -5.7\n  - 三菱商事: -5.03\n  - 豊田通商: -4.83\n  - ダイキン工業: -3.86\n  - スズキ: -3.15\n  - 三井不動産: -2.82\n  - 伊藤忠商事: -2.6\n  - 日立製作所: -2.38\n  - 小松製作所: -2.08\n  - 丸紅: -1.94\n  - 本田技研工業: -1.91\n  - オリエンタルランド: -1.89\n  - 住友商事: -1.71\n  - 日立建機: -1.68\n  - Ｔ＆Ｄホールディングス: -1.64\n  - ＩＮＰＥＸ: -1.52\n  - ＡＲＣＨＩＯＮ: -1.51\n  - ＩＨＩ: -1.5\n  - ニトリホールディングス: -1.47\n  - 花王: -1.44\n  - 武田薬品工業: -1.37\n  - 大林組: -1.37\n  - 三菱重工業: -1.37\n  - 大成建設: -1.27\n  - 日本ハム: -1.24"
}